cvhelper/__init__.py
cvhelper/display.py
cvhelper/image_operations.py
cvhelper/misc_functions.py
cvhelper/model.py
cvhelper/tracking.py
cvhelper/utils.py
cvhelper/video.py
cvhelper-0.1.0.dist-info/LICENSE
cvhelper-0.1.0.dist-info/METADATA
cvhelper-0.1.0.dist-info/WHEEL
cvhelper-0.1.0.dist-info/top_level.txt
cvhelper-0.1.0.dist-info/RECORD
