Metadata-Version: 2.1
Name: cvhelper
Version: 0.1.0
Summary: A helper package for OpenCV
Home-page: https://github.com/anbergem/cvhelper
Author: Andreas Bergem
Author-email: bergem.andreas@gmail.com
License: MIT
Keywords: opencv
Platform: UNKNOWN
Classifier: Programming Language :: Python :: 3.7
Classifier: License :: OSI Approved :: MIT License
Classifier: Operating System :: OS Independent
Classifier: Topic :: Scientific/Engineering :: Image Recognition
Requires-Python: >=3.7
Requires-Dist: numpy (<=1.15.3)
Requires-Dist: opencv-python (<=3.4.3.18)
